adding_srinivas/__init__.py
adding_srinivas/index2.py
adding_srinivas-0.0.5.dist-info/METADATA
adding_srinivas-0.0.5.dist-info/WHEEL
adding_srinivas-0.0.5.dist-info/top_level.txt
adding_srinivas-0.0.5.dist-info/RECORD
