Metadata-Version: 2.2
Name: adding_srinivas
Version: 0.0.5
Summary: add number package
Author: srinivas
Keywords: python,video,videostream
Classifier: Development Status :: 1 - Planning
Classifier: Intended Audience :: Developers
Classifier: Operating System :: Unix
Classifier: Operating System :: MacOS :: MacOS X
Classifier: Operating System :: Microsoft :: Windows
Dynamic: author
Dynamic: classifier
Dynamic: keywords
Dynamic: summary
